ocrbridge/__init__.py
ocrbridge/core/__init__.py
ocrbridge/core/base.py
ocrbridge/core/exceptions.py
ocrbridge/core/models.py
ocrbridge/core/validation.py
ocrbridge/core/utils/__init__.py
ocrbridge/core/utils/hocr.py
ocrbridge/core/utils/pdf.py
ocrbridge_core-3.1.1.dist-info/METADATA
ocrbridge_core-3.1.1.dist-info/WHEEL
ocrbridge_core-3.1.1.dist-info/licenses/LICENSE
ocrbridge_core-3.1.1.dist-info/RECORD
