Metadata-Version: 2.4
Name: ocrbridge-core
Version: 3.1.1
Summary: Core interfaces and utilities for OCR Bridge engine packages
License: MIT
License-File: LICENSE
Requires-Python: >=3.10
Requires-Dist: pdf2image>=1.17.0
Requires-Dist: pillow>=12.0.0
Requires-Dist: pydantic>=2.0.0
Provides-Extra: build
Requires-Dist: python-semantic-release>=10.5.2; extra == 'build'
Provides-Extra: test
Requires-Dist: pytest~=9.0; extra == 'test'
